[
    {
        "and": 3.0,
        "false": 0.0,
        "exists": 0.0,
        "int": 4.0,
        "float": 0.0,
        "as": 0.0,
        "n_quants": 1.0,
        "zero_ar": 0.0,
        "if": 0.0,
        "goal": "Ineq1",
        "n_branches": 19.0,
        "iff": 0.0,
        "n_ops": 18.0,
        "var": 15.0,
        "size": 38.0,
        "avg_op_arity": 2.055556,
        "theory": "BuildMaze",
        "n_preds": 0.0,
        "forall": 1.0,
        "let": 0.0,
        "func": 12.0,
        "not": 0.0,
        "true": 0.0,
        "case": 0.0,
        "divisor": 18.0,
        "eps": 0.0,
        "depth": 9.0,
        "wild": 0.0,
        "or": 0.0,
        "impl": 3.0
    },
    {
        "and": 30.0,
        "false": 0.0,
        "exists": 0.0,
        "int": 14.0,
        "float": 0.0,
        "as": 0.0,
        "n_quants": 8.0,
        "zero_ar": 0.0,
        "if": 0.0,
        "goal": "WP_parameter add_edge_and_union",
        "n_branches": 122.0,
        "iff": 4.0,
        "n_ops": 121.0,
        "var": 108.0,
        "size": 251.0,
        "avg_op_arity": 2.136752,
        "theory": "BuildMaze",
        "n_preds": 4.0,
        "forall": 8.0,
        "let": 0.0,
        "func": 70.0,
        "not": 4.0,
        "true": 0.0,
        "case": 0.0,
        "divisor": 117.0,
        "eps": 0.0,
        "depth": 21.0,
        "wild": 0.0,
        "or": 4.0,
        "impl": 9.0
    },
    {
        "and": 76.0,
        "false": 0.0,
        "exists": 0.0,
        "int": 53.0,
        "float": 0.0,
        "as": 0.0,
        "n_quants": 23.0,
        "zero_ar": 0.0,
        "if": 7.0,
        "goal": "WP_parameter build_maze",
        "n_branches": 319.0,
        "iff": 8.0,
        "n_ops": 332.0,
        "var": 266.0,
        "size": 674.0,
        "avg_op_arity": 2.123028,
        "theory": "BuildMaze",
        "n_preds": 15.0,
        "forall": 23.0,
        "let": 3.0,
        "func": 206.0,
        "not": 3.0,
        "true": 0.0,
        "case": 0.0,
        "divisor": 317.0,
        "eps": 0.0,
        "depth": 49.0,
        "wild": 0.0,
        "or": 0.0,
        "impl": 29.0
    }
]