[
    {
        "and": 0.0,
        "false": 0.0,
        "exists": 0.0,
        "int": 0.0,
        "float": 0.0,
        "as": 0.0,
        "n_quants": 1.0,
        "zero_ar": 0.0,
        "if": 0.0,
        "goal": "gcd_sub",
        "n_branches": 5.0,
        "iff": 0.0,
        "n_ops": 4.0,
        "var": 5.0,
        "size": 10.0,
        "avg_op_arity": 2.25,
        "theory": "ParallelGCD",
        "n_preds": 0.0,
        "forall": 1.0,
        "let": 0.0,
        "func": 4.0,
        "not": 0.0,
        "true": 0.0,
        "case": 0.0,
        "divisor": 4.0,
        "eps": 0.0,
        "depth": 5.0,
        "wild": 0.0,
        "or": 0.0,
        "impl": 0.0
    },
    {
        "and": 25.0,
        "false": 0.0,
        "exists": 0.0,
        "int": 14.0,
        "float": 0.0,
        "as": 0.0,
        "n_quants": 5.0,
        "zero_ar": 1.0,
        "if": 4.0,
        "goal": "WP_parameter parallel_gcd",
        "n_branches": 89.0,
        "iff": 0.0,
        "n_ops": 86.0,
        "var": 74.0,
        "size": 179.0,
        "avg_op_arity": 2.170732,
        "theory": "ParallelGCD",
        "n_preds": 4.0,
        "forall": 5.0,
        "let": 0.0,
        "func": 52.0,
        "not": 1.0,
        "true": 0.0,
        "case": 0.0,
        "divisor": 82.0,
        "eps": 0.0,
        "depth": 16.0,
        "wild": 0.0,
        "or": 0.0,
        "impl": 4.0
    },
    {
        "and": 0.0,
        "false": 0.0,
        "exists": 0.0,
        "int": 0.0,
        "float": 0.0,
        "as": 0.0,
        "n_quants": 1.0,
        "zero_ar": 0.0,
        "if": 0.0,
        "goal": "gcd_sub",
        "n_branches": 5.0,
        "iff": 0.0,
        "n_ops": 4.0,
        "var": 5.0,
        "size": 10.0,
        "avg_op_arity": 2.25,
        "theory": "Interleaving",
        "n_preds": 0.0,
        "forall": 1.0,
        "let": 0.0,
        "func": 4.0,
        "not": 0.0,
        "true": 0.0,
        "case": 0.0,
        "divisor": 4.0,
        "eps": 0.0,
        "depth": 5.0,
        "wild": 0.0,
        "or": 0.0,
        "impl": 0.0
    },
    {
        "and": 24.0,
        "false": 0.0,
        "exists": 0.0,
        "int": 6.0,
        "float": 0.0,
        "as": 0.0,
        "n_quants": 9.0,
        "zero_ar": 9.0,
        "if": 2.0,
        "goal": "WP_parameter step",
        "n_branches": 180.0,
        "iff": 0.0,
        "n_ops": 153.0,
        "var": 165.0,
        "size": 333.0,
        "avg_op_arity": 2.18,
        "theory": "Interleaving",
        "n_preds": 3.0,
        "forall": 9.0,
        "let": 6.0,
        "func": 93.0,
        "not": 0.0,
        "true": 0.0,
        "case": 1.0,
        "divisor": 150.0,
        "eps": 0.0,
        "depth": 19.0,
        "wild": 0.0,
        "or": 6.0,
        "impl": 21.0
    },
    {
        "and": 33.0,
        "false": 0.0,
        "exists": 0.0,
        "int": 63.0,
        "float": 0.0,
        "as": 0.0,
        "n_quants": 7.0,
        "zero_ar": 25.0,
        "if": 62.0,
        "goal": "WP_parameter parallel_gcd",
        "n_branches": 429.0,
        "iff": 0.0,
        "n_ops": 341.0,
        "var": 341.0,
        "size": 752.0,
        "avg_op_arity": 2.691756,
        "theory": "Interleaving",
        "n_preds": 62.0,
        "forall": 7.0,
        "let": 5.0,
        "func": 218.0,
        "not": 2.0,
        "true": 0.0,
        "case": 0.0,
        "divisor": 279.0,
        "eps": 0.0,
        "depth": 33.0,
        "wild": 0.0,
        "or": 9.0,
        "impl": 12.0
    }
]